quantumsecurity/__init__.py
quantumsecurity/main.py
quantumsecurity-0.0.5.dist-info/METADATA
quantumsecurity-0.0.5.dist-info/WHEEL
quantumsecurity-0.0.5.dist-info/top_level.txt
quantumsecurity-0.0.5.dist-info/RECORD
